safe_sql/__init__.py
safe_sql/main.py
safe_sql-0.1.0.dist-info/entry_points.txt
safe_sql-0.1.0.dist-info/METADATA
safe_sql-0.1.0.dist-info/WHEEL
safe_sql-0.1.0.dist-info/RECORD
