Metadata-Version: 2.1
Name: safe-sql
Version: 0.1.0
Summary: Data is gold, don't make stupid mistakes
License: MIT
Author: Yash Srivastava
Author-email: ysrivastava82@gmail.com
Requires-Python: >=3.11,<4.0
Classifier: License :: OSI Approved :: MIT License
Classifier: Programming Language :: Python :: 3
Classifier: Programming Language :: Python :: 3.11
Classifier: Programming Language :: Python :: 3.12
Requires-Dist: click (>=8.1.7,<9.0.0)
Requires-Dist: sqlalchemy (>=2.0.32,<3.0.0)
